Workbook

Sheet Help
A1: [режим_сопоставления] (Match Mode)
A2: Qiymat | B2: Nomi | C2: Nima qiladi | D2: Qachon ishlatiladi
A3: 0 | B3: Exact match | C3: Faqat aynan teng qiymatni topadi | D3: Default (eng ko‘p ishlatiladi)
A4: -1 | B4: Exact yoki kichik | C4: Topilmasa, undan kichik eng yaqin qiymat | D4: Chegara, bonus, narx diapazoni
A5: 1 | B5: Exact yoki katta | C5: Topilmasa, undan katta eng yaqin qiymat | D5: Tarif, minimal qiymat
A6: 2 | B6: Wildcard match | C6: * va ? bilan ichidan qidiradi | D6: Matn qidirish
A8: [режим_поиска] (Search Mode)
A9: Qiymat | B9: Nomi | C9: Nima qiladi | D9: Qachon ishlatiladi
A10: 1 | B10: Oldindan qidiruv | C10: Yuqoridan pastga qidiradi | D10: Default
A11: -1 | B11: Reverse qidiruv | C11: Pastdan yuqoriga qidiradi | D11: Oxirgi qiymatni olish
A12: 2 | B12: Binary (o‘sish) | C12: Tez qidiradi (sorted data) | D12: Katta dataset
A13: -2 | B13: Binary (kamayish) | C13: Tez qidiradi (teskari sorted) | D13: Maxsus holat
A16: ПРОСМОТРX(искомое_значение; просматриваемый_массив; возвращаемый_массив; [если_не_найдено]; [режим_сопоставления]; [режим_поиска])

Sheet 1
A2: A va B lar ishtirokida to'ldiramiz
A3: Товар | B3: Поставщик | C3: Категория | D3: Цена
A4: Гречка | B4: =_xlfn.XLOOKUP(A4,B10:B15,C10:C15) -> NutriFix | C4: =_xlfn.XLOOKUP(A4,B10:B15,A10:A15,) -> Крупы | D4: =_xlfn.XLOOKUP(A4,B18:G18,B19:G19) -> 1.4
A5: Шоколад | B5: =_xlfn.XLOOKUP(A5,B10:B15,C10:C15) -> mymeal | C5: =_xlfn.XLOOKUP(A5,B10:B15,A10:A15) -> Сладости | D5: =_xlfn.XLOOKUP(A5,B18:G18,B19:G19) -> 0.55
A6: Курага | B6: =_xlfn.XLOOKUP(A6,B10:B15,C10:C15) -> Sweetables | C6: =_xlfn.XLOOKUP(A6,B10:B15,A10:A15) -> Сухофрукты | D6: =_xlfn.XLOOKUP(G18,B18:G18,B19:G19) -> 1.19
A8: A jadval
A9: Категория | B9: Товар | C9: Поставщик
A10: Крупы | B10: Гречка | C10: NutriFix
A11: Крупы | B11: Рис | C11: NutriFix
A12: Сладости | B12: Зефир | C12: Sweetables
A13: Сладости | B13: Шоколад | C13: mymeal
A14: Сухофрукты | B14: Изюм | C14: Sweetables
A15: Сухофрукты | B15: Курага | C15: Sweetables
A17: B jadval
A18: Товар | B18: Гречка | C18: Рис | D18: Зефир | E18: Шоколад | F18: Изюм | G18: Курага
A19: Цена/шт. (€) | B19: 1.4 | C19: 0.96 | D19: 0.65 | E19: 0.55 | F19: 0.99 | G19: 1.19

Sheet 2
A2: ТОВАР | B2: Boshida sotib olingan tovar sanasi | C2: Oxirgi savdo sanasi | E2: Дата | F2: Поставщик | G2: Категория | H2: Товар | I2: Цена за штуку | J2: Количество | K2: Выручка
A3: Изюм | B3: =_xlfn.XLOOKUP(A3,Table_1[Товар],Table_1[Дата]) -> 44508 | C3: =_xlfn.XLOOKUP(A3,Table_1[Товар],Table_1[Дата],"sotib olinmagan",0,-1) -> 44525 | E3: 44501 | F3: NutriFix | G3: Крупы | H3: Гречка | I3: 1.4 | J3: 120 | K3: 168
A4: Кофе | B4: =_xlfn.XLOOKUP(A4,Table_1[Товар],Table_1[Дата],"Sotib olinmagan") -> Sotib olinmagan | C4: =_xlfn.XLOOKUP(A4,Table_1[Товар],Table_1[Дата],"Sotib olinmagan",0,-1) -> Sotib olinmagan | E4: 44501 | F4: NutriFix | G4: Крупы | H4: Рис | I4: 0.96 | J4: 130 | K4: 124.8
A5: Рис | B5: =_xlfn.XLOOKUP(A5,Table_1[Товар],Table_1[Дата]) -> 44501 | C5: =_xlfn.XLOOKUP(A5,Table_1[Товар],Table_1[Дата],"sotib olinmagan",0,-1) -> 44520 | E5: 44502 | F5: Sweetables | G5: Сладости | H5: Зефир | I5: 0.65 | J5: 20 | K5: 13
A6: Шоколад | B6: =_xlfn.XLOOKUP(A6,Table_1[Товар],Table_1[Дата]) -> 44506 | C6: =_xlfn.XLOOKUP(A6,Table_1[Товар],Table_1[Дата],"sotib olinmagan",0,-1) -> 44514 | E6: 44503 | F6: NutriFix | G6: Крупы | H6: Рис | I6: 0.96 | J6: 108 | K6: 103.68
E7: 44504 | F7: NutriFix | G7: Крупы | H7: Гречка | I7: 1.4 | J7: 216 | K7: 302.4
E8: 44505 | F8: Sweetables | G8: Сладости | H8: Зефир | I8: 0.65 | J8: 83 | K8: 53.95
E9: 44505 | F9: NutriFix | G9: Крупы | H9: Гречка | I9: 1.4 | J9: 203 | K9: 284.2
E10: 44506 | F10: mymeal | G10: Сладости | H10: Шоколад | I10: 0.55 | J10: 11 | K10: 6.05
E11: 44508 | F11: Sweetables | G11: Сухофрукты | H11: Изюм | I11: 0.99 | J11: 265 | K11: 262.35
E12: 44509 | F12: Sweetables | G12: Сухофрукты | H12: Курага | I12: 1.19 | J12: 86 | K12: 102.34
E13: 44511 | F13: NutriFix | G13: Крупы | H13: Гречка | I13: 1.4 | J13: 29 | K13: 40.6
E14: 44512 | F14: NutriFix | G14: Крупы | H14: Гречка | I14: 1.4 | J14: 61 | K14: 85.4
E15: 44514 | F15: mymeal | G15: Сладости | H15: Шоколад | I15: 0.55 | J15: 34 | K15: 18.7
E16: 44520 | F16: NutriFix | G16: Крупы | H16: Рис | I16: 0.96 | J16: 568 | K16: 545.28
E17: 44525 | F17: Sweetables | G17: Сухофрукты | H17: Изюм | I17: 0.99 | J17: 55 | K17: 54.45
E18: 44527 | F18: Sweetables | G18: Сухофрукты | H18: Курага | I18: 1.19 | J18: 41 | K18: 48.79

Sheet 3
A2: Студент | B2: Ball | C2: Baho | E2: Ball | F2: Baho
A3: Студент A | B3: 75 | C3: =_xlfn.XLOOKUP(B3, $E$3:$E$6, $F$3:$F$6, , -1) -> 4 | E3: 0 | F3: 2
A4: Студент B | B4: 86 | C4: =_xlfn.XLOOKUP(B4, $E$3:$E$6, $F$3:$F$6, , -1) -> 4 | E4: 60 | F4: 3
A5: Студент C | B5: 96 | C5: =_xlfn.XLOOKUP(B5, $E$3:$E$6, $F$3:$F$6, , -1) -> 5 | E5: 75 | F5: 4
A6: Студент D | B6: 94 | C6: =_xlfn.XLOOKUP(B6, $E$3:$E$6, $F$3:$F$6, , -1) -> 5 | E6: 90 | F6: 5
A7: Студент E | B7: 53 | C7: =_xlfn.XLOOKUP(B7, $E$3:$E$6, $F$3:$F$6, , -1) -> 2
A8: Студент F | B8: 75 | C8: =_xlfn.XLOOKUP(B8, $E$3:$E$6, $F$3:$F$6, , -1) -> 4
A9: Студент G | B9: 99 | C9: =_xlfn.XLOOKUP(B9, $E$3:$E$6, $F$3:$F$6, , -1) -> 5
A10: Студент H | B10: 100 | C10: =_xlfn.XLOOKUP(B10, $E$3:$E$6, $F$3:$F$6, , -1) -> 5
A11: Студент I | B11: 64 | C11: =_xlfn.XLOOKUP(B11, $E$3:$E$6, $F$3:$F$6, , -1) -> 3
A12: Студент J | B12: 45 | C12: =_xlfn.XLOOKUP(B12, $E$3:$E$6, $F$3:$F$6, , -1) -> 2
A13: Студент K | B13: 80 | C13: =_xlfn.XLOOKUP(B13, $E$3:$E$6, $F$3:$F$6, , -1) -> 4
A14: Студент L | B14: 73 | C14: =_xlfn.XLOOKUP(B14, $E$3:$E$6, $F$3:$F$6, , -1) -> 3
A15: Студент M | B15: 83 | C15: =_xlfn.XLOOKUP(B15, $E$3:$E$6, $F$3:$F$6, , -1) -> 4
A16: Студент N | B16: 64 | C16: =_xlfn.XLOOKUP(B16, $E$3:$E$6, $F$3:$F$6, , -1) -> 3
A17: Студент O | B17: 40 | C17: =_xlfn.XLOOKUP(B17, $E$3:$E$6, $F$3:$F$6, , -1) -> 2
A18: Студент P | B18: 74 | C18: =_xlfn.XLOOKUP(B18, $E$3:$E$6, $F$3:$F$6, , -1) -> 3
... A22: Студент T | B22: 81 | C22: =_xlfn.XLOOKUP(B22, $E$3:$E$6, $F$3:$F$6, , -1) -> 4

Sheet 4
A2: Акция | B2: Курс | D2: Акция | E2: Курс
A3: Adobe Inc. | B3: 674.08 | D3: Adobe | E3: =_xlfn.XLOOKUP("*" & D3 & "*", $A$3:$A$11, $B$3:$B$11, "Topilmadi", 2) -> 674.08
A4: Class C Alphabet Inc. | B4: 2973.66 | D4: Alphabet | E4: =_xlfn.XLOOKUP("*" & D4 & "*", $A$3:$A$11, $B$3:$B$11, "Topilmadi", 2) -> 2973.66
A5: Amazon.com Inc. | B5: 3477 | D5: Amazon | E5: =_xlfn.XLOOKUP("*" & D5 & "*", $A$3:$A$11, $B$3:$B$11, "Topilmadi", 2) -> 3477
A6: Apple Inc. | B6: 150.96 | D6: Apple | E6: =_xlfn.XLOOKUP("*" & D6 & "*", $A$3:$A$11, $B$3:$B$11, "Topilmadi", 2) -> 150.96
A7: Bank of America Corp | B7: 47.33 | D7: Microsoft Corp. | E7: =_xlfn.XLOOKUP("*" & D7 & "*", $A$3:$A$11, $B$3:$B$11, "Topilmadi", 2) -> 336.44
A8: Exxon Mobil Corp. | B8: 64.41 | D8: Tesla | E8: =_xlfn.XLOOKUP("*" & D8 & "*", $A$3:$A$11, $B$3:$B$11, "Topilmadi", 2) -> 1229.91
A9: General Motors | B9: 58.64
A10: Microsoft Corp. | B10: 336.44
A11: Tesla, Inc. | B11: 1229.91

Sheet ID
A1: Bo'lim | B1: Ism Familiya
A2: Sales | B2: Jasur Aliyev
A3: Sales | B3: Bekzod Rustamov
A4: Sales | B4: Odil Abdullayev
A5: Procurement | B5: Shodlik Nurmatov
A6: Finance | B6: Aziz Raxmatov
A7: Finance | B7: Ulugbek Soliyev
A8: Procurement | B8: Jalon Akbarov
A9: Sales | B9: Sarvar Raxmonov
A10: Finance | B10: Sardor Karimov
A11: Procurement | B11: Abduraxmon Toirov
A12: Sales | B12: Sarvar Karimov
... A31: Sales | B31: Ilhom Rahimov

Sheet Salary
A1: Ism Familiya | B1: Maoshi | C1: Bonus | D1: Bonus summasi | E1: Jami | F1: Lavozimi | G1: ID
A2: Jasur Nurmatov | B2: 8181 | C2: =_xlfn.XLOOKUP(A2,'H&V'!$B$4:$B$33,'H&V'!$A$4:$A$33,"Topilmadi") -> 0.24 | D2: =B2*(C2/100) -> 19.6344 | E2: =B2+D2 -> 8200.6344 | F2: =_xlfn.XLOOKUP(A2,ID!$B$2:$B$31,ID!$A$2:$A$31) -> Sales | G2: =RIGHT(_xlfn.XLOOKUP(A2, 'H&V'!$E$5:$AH$5, 'H&V'!$E$3:$AH$3), 1) -> 4
A3: Sarvar Karimov | B3: 8451 | C3: =_xlfn.XLOOKUP(A3,'H&V'!$B$4:$B$33,'H&V'!$A$4:$A$33,"Topilmadi") -> 0.24 | D3: =B3*(C3/100) -> 20.2824 | E3: =B3+D3 -> 8471.2824 | F3: =_xlfn.XLOOKUP(A3,ID!$B$2:$B$31,ID!$A$2:$A$31) -> Sales | G3: =RIGHT(_xlfn.XLOOKUP(A3,'H&V'!$E$5:$AH$5,'H&V'!$E$3:$AH$3),1) -> 0
A4: Dilshod Raxmonov | B4: 8020 | C4: =_xlfn.XLOOKUP(A4,'H&V'!$B$4:$B$33,'H&V'!$A$4:$A$33,"Topilmadi") -> 0.23 | D4: =B4*(C4/100) -> 18.446 | E4: =B4+D4 -> 8038.446 | F4: =_xlfn.XLOOKUP(A4,ID!$B$2:$B$31,ID!$A$2:$A$31) -> Sales | G4: =RIGHT(_xlfn.XLOOKUP(A4,'H&V'!$E$5:$AH$5,'H&V'!$E$3:$AH$3),1) -> 8
A5: Jashon Abdullaev | B5: 2838 | C5: =_xlfn.XLOOKUP(A5,'H&V'!$B$4:$B$33,'H&V'!$A$4:$A$33,"Topilmadi") -> 0.1 | D5: =B5*(C5/100) -> 2.838 | E5: =B5+D5 -> 2840.838 | F5: =_xlfn.XLOOKUP(A5,ID!$B$2:$B$31,ID!$A$2:$A$31) -> Sales | G5: =RIGHT(_xlfn.XLOOKUP(A5,'H&V'!$E$5:$AH$5,'H&V'!$E$3:$AH$3),1) -> 4
A6: Shoxrux Yuldashev | B6: 6609 | C6: =_xlfn.XLOOKUP(A6,'H&V'!$B$4:$B$33,'H&V'!$A$4:$A$33,"Topilmadi") -> 0.1 | D6: =B6*(C6/100) -> 6.609 | E6: =B6+D6 -> 6615.609 | F6: =_xlfn.XLOOKUP(A6,ID!$B$2:$B$31,ID!$A$2:$A$31) -> Sales | G6: =RIGHT(_xlfn.XLOOKUP(A6,'H&V'!$E$5:$AH$5,'H&V'!$E$3:$AH$3),1) -> 3
A7: Akmal Toshpulatov | B7: 5957 | C7: =_xlfn.XLOOKUP(A7,'H&V'!$B$4:$B$33,'H&V'!$A$4:$A$33,"Topilmadi") -> 0.09 | D7: =B7*(C7/100) -> 5.3613 | E7: =B7+D7 -> 5962.3613 | F7: =_xlfn.XLOOKUP(A7,ID!$B$2:$B$31,ID!$A$2:$A$31) -> Sales | G7: =RIGHT(_xlfn.XLOOKUP(A7,'H&V'!$E$5:$AH$5,'H&V'!$E$3:$AH$3),1) -> 4
A8: Bekzod Rustamov | B8: 2415 | C8: =_xlfn.XLOOKUP(A8,'H&V'!$B$4:$B$33,'H&V'!$A$4:$A$33,"Topilmadi") -> 0.09 | D8: =B8*(C8/100) -> 2.1735 | E8: =B8+D8 -> 2417.1735 | F8: =_xlfn.XLOOKUP(A8,ID!$B$2:$B$31,ID!$A$2:$A$31) -> Sales | G8: =RIGHT(_xlfn.XLOOKUP(A8,'H&V'!$E$5:$AH$5,'H&V'!$E$3:$AH$3),1) -> 2
A9: Murod Karimov | B9: 2408 | C9: =_xlfn.XLOOKUP(A9,'H&V'!$B$4:$B$33,'H&V'!$A$4:$A$33,"Topilmadi") -> 0.27 | D9: =B9*(C9/100) -> 6.5016 | E9: =B9+D9 -> 2414.5016 | F9: =_xlfn.XLOOKUP(A9,ID!$B$2:$B$31,ID!$A$2:$A$31) -> Sales | G9: =RIGHT(_xlfn.XLOOKUP(A9,'H&V'!$E$5:$AH$5,'H&V'!$E$3:$AH$3),1) -> 7
A10: Ilhom Rahimov | B10: 2083 | C10: =_xlfn.XLOOKUP(A10,'H&V'!$B$4:$B$33,'H&V'!$A$4:$A$33,"Topilmadi") -> 0.25 | D10: =B10*(C10/100) -> 5.2075 | E10: =B10+D10 -> 2088.2075 | F10: =_xlfn.XLOOKUP(A10,ID!$B$2:$B$31,ID!$A$2:$A$31) -> Sales | G10: =RIGHT(_xlfn.XLOOKUP(A10, 'H&V'!$E$5:$AH$5, 'H&V'!$E$3:$AH$3), 1) -> 0
A11: Jasur Aliyev | B11: 5742 | C11: =_xlfn.XLOOKUP(A11,'H&V'!$B$4:$B$33,'H&V'!$A$4:$A$33,"Topilmadi") -> 0.25 | D11: =B11*(C11/100) -> 14.355 | E11: =B11+D11 -> 5756.355 | F11: =_xlfn.XLOOKUP(A11,ID!$B$2:$B$31,ID!$A$2:$A$31) -> Sales | G11: =RIGHT(_xlfn.XLOOKUP(A11,'H&V'!$E$5:$AH$5,'H&V'!$E$3:$AH$3),1) -> 5
A12: Odil Abdullayev | B12: 5112 | C12: =_xlfn.XLOOKUP(A12,'H&V'!$B$4:$B$33,'H&V'!$A$4:$A$33,"Topilmadi") -> 0.25 | D12: =B12*(C12/100) -> 12.78 | E12: =B12+D12 -> 5124.78 | F12: =_xlfn.XLOOKUP(A12,ID!$B$2:$B$31,ID!$A$2:$A$31) -> Sales | G12: =RIGHT(_xlfn.XLOOKUP(A12,'H&V'!$E$5:$AH$5,'H&V'!$E$3:$AH$3),1) -> 6
A13: Sarvar Raxmonov | B13: 5995 | C13: =_xlfn.XLOOKUP(A13,'H&V'!$B$4:$B$33,'H&V'!$A$4:$A$33,"Topilmadi") -> 0.25 | D13: =B13*(C13/100) -> 14.9875 | E13: =B13+D13 -> 6009.9875 | F13: =_xlfn.XLOOKUP(A13,ID!$B$2:$B$31,ID!$A$2:$A$31) -> Sales | G13: =RIGHT(_xlfn.XLOOKUP(A13,'H&V'!$E$5:$AH$5,'H&V'!$E$3:$AH$3),1) -> 1
A14: Abbos Karimov | B14: 8444 | C14: =_xlfn.XLOOKUP(A14,'H&V'!$B$4:$B$33,'H&V'!$A$4:$A$33,"Topilmadi") -> 0.06 | D14: =B14*(C14/100) -> 5.0664 | E14: =B14+D14 -> 8449.0664 | F14: =_xlfn.XLOOKUP(A14,ID!$B$2:$B$31,ID!$A$2:$A$31) -> Procurement | G14: =RIGHT(_xlfn.XLOOKUP(A14,'H&V'!$E$5:$AH$5,'H&V'!$E$3:$AH$3),1) -> 1
A15: Dilshod Rustamov | B15: 3106 | C15: =_xlfn.XLOOKUP(A15,'H&V'!$B$4:$B$33,'H&V'!$A$4:$A$33,"Topilmadi") -> 0.09 | D15: =B15*(C15/100) -> 2.7954 | E15: =B15+D15 -> 3108.7954 | F15: =_xlfn.XLOOKUP(A15,ID!$B$2:$B$31,ID!$A$2:$A$31) -> Procurement | G15: =RIGHT(_xlfn.XLOOKUP(A15,'H&V'!$E$5:$AH$5,'H&V'!$E$3:$AH$3),1) -> 2
A16: Javlon Akbarov | B16: 8926 | C16: =_xlfn.XLOOKUP(A16,'H&V'!$B$4:$B$33,'H&V'!$A$4:$A$33,"Topilmadi") -> 0.18 | D16: =B16*(C16/100) -> 16.0668 | E16: =B16+D16 -> 8942.0668 | F16: =_xlfn.XLOOKUP(A16,ID!$B$2:$B$31,ID!$A$2:$A$31,"Topilmadi") -> Topilmadi | G16: =RIGHT(_xlfn.XLOOKUP(A16,'H&V'!$E$5:$AH$5,'H&V'!$E$3:$AH$3),1) -> 7
A17: Shodlik Nurmatov | B17: 8138 | C17: =_xlfn.XLOOKUP(A17,'H&V'!$B$4:$B$33,'H&V'!$A$4:$A$33,"Topilmadi") -> 0.17 | D17: =B17*(C17/100) -> 13.8346 | E17: =B17+D17 -> 8151.8346 | F17: =_xlfn.XLOOKUP(A17,ID!$B$2:$B$31,ID!$A$2:$A$31) -> Procurement | G17: =RIGHT(_xlfn.XLOOKUP(A17,'H&V'!$E$5:$AH$5,'H&V'!$E$3:$AH$3),1) -> 5
A18: Abduraxmon Toirov | B18: 2167 | C18: =_xlfn.XLOOKUP(A18,'H&V'!$B$4:$B$33,'H&V'!$A$4:$A$33,"Topilmadi") -> 0.14 | D18: =B18*(C18/100) -> 3.0338 | E18: =B18+D18 -> 2170.0338 | F18: =_xlfn.XLOOKUP(A18,ID!$B$2:$B$31,ID!$A$2:$A$31) -> Procurement | G18: =RIGHT(_xlfn.XLOOKUP(A18,'H&V'!$E$5:$AH$5,'H&V'!$E$3:$AH$3),1) -> 2
A19: Jashon Alimov | B19: 2616 | C19: =_xlfn.XLOOKUP(A19,'H&V'!$B$4:$B$33,'H&V'!$A$4:$A$33,"Topilmadi") -> 0.14 | D19: =B19*(C19/100) -> 3.6624 | E19: =B19+D19 -> 2619.6624 | F19: =_xlfn.XLOOKUP(A19,ID!$B$2:$B$31,ID!$A$2:$A$31) -> Procurement | G19: =RIGHT(_xlfn.XLOOKUP(A19,'H&V'!$E$5:$AH$5,'H&V'!$E$3:$AH$3),1) -> 9
A20: Bekzod Abdullaev | B20: 9032 | C20: =_xlfn.XLOOKUP(A20,'H&V'!$B$4:$B$33,'H&V'!$A$4:$A$33,"Topilmadi") -> 0.02 | D20: =B20*(C20/100) -> 1.8064 | E20: =B20+D20 -> 9033.8064 | F20: =_xlfn.XLOOKUP(A20,ID!$B$2:$B$31,ID!$A$2:$A$31) -> Finance | G20: =RIGHT(_xlfn.XLOOKUP(A20,'H&V'!$E$5:$AH$5,'H&V'!$E$3:$AH$3),1) -> 3
A21: Ulugbek Soliyev | B21: 8966 | C21: =_xlfn.XLOOKUP(A21,'H&V'!$B$4:$B$33,'H&V'!$A$4:$A$33,"Topilmadi") -> 0.01 | D21: =B21*(C21/100) -> 0.8966 | E21: =B21+D21 -> 8966.8966 | F21: =_xlfn.XLOOKUP(A21,ID!$B$2:$B$31,ID!$A$2:$A$31) -> Finance | G21: =RIGHT(_xlfn.XLOOKUP(A21,'H&V'!$E$5:$AH$5,'H&V'!$E$3:$AH$3),1) -> 4
A22: Dilmurod Akbarov | B22: 9619 | C22: =_xlfn.XLOOKUP(A22,'H&V'!$B$4:$B$33,'H&V'!$A$4:$A$33,"Topilmadi") -> 0.23 | D22: =B22*(C22/100) -> 22.1237 | E22: =B22+D22 -> 9641.1237 | F22: =_xlfn.XLOOKUP(A22,ID!$B$2:$B$31,ID!$A$2:$A$31) -> Finance | G22: =RIGHT(_xlfn.XLOOKUP(A22,'H&V'!$E$5:$AH$5,'H&V'!$E$3:$AH$3),1) -> 9
A23: Aziz Raxmatov | B23: 4166 | C23: =_xlfn.XLOOKUP(A23,'H&V'!$B$4:$B$33,'H&V'!$A$4:$A$33,"Topilmadi") -> 0.21 | D23: =B23*(C23/100) -> 8.7486 | E23: =B23+D23 -> 4174.7486 | F23: =_xlfn.XLOOKUP(A23,ID!$B$2:$B$31,ID!$A$2:$A$31) -> Finance | G23: =RIGHT(_xlfn.XLOOKUP(A23,'H&V'!$E$5:$AH$5,'H&V'!$E$3:$AH$3),1) -> 1
A24: Javlon Soliyev | B24: 2400 | C24: =_xlfn.XLOOKUP(A24,'H&V'!$B$4:$B$33,'H&V'!$A$4:$A$33,"Topilmadi") -> 0.2 | D24: =B24*(C24/100) -> 4.8 | E24: =B24+D24 -> 2404.8 | F24: =_xlfn.XLOOKUP(A24,ID!$B$2:$B$31,ID!$A$2:$A$31) -> Finance | G24: =RIGHT(_xlfn.XLOOKUP(A24,'H&V'!$E$5:$AH$5,'H&V'!$E$3:$AH$3),1) -> 1
A25: Sardor Karimov | B25: 8904 | C25: =_xlfn.XLOOKUP(A25,'H&V'!$B$4:$B$33,'H&V'!$A$4:$A$33,"Topilmadi") -> 0.19 | D25: =B25*(C25/100) -> 16.9176 | E25: =B25+D25 -> 8920.9176 | F25: =_xlfn.XLOOKUP(A25,ID!$B$2:$B$31,ID!$A$2:$A$31) -> Finance | G25: =RIGHT(_xlfn.XLOOKUP(A25,'H&V'!$E$5:$AH$5,'H&V'!$E$3:$AH$3),1) -> 6
A26: Komron Raxmonov | B26: 9167 | C26: =_xlfn.XLOOKUP(A26,'H&V'!$B$4:$B$33,'H&V'!$A$4:$A$33,"Topilmadi") -> 0.18 | D26: =B26*(C26/100) -> 16.5006 | E26: =B26+D26 -> 9183.5006 | F26: =_xlfn.XLOOKUP(A26,ID!$B$2:$B$31,ID!$A$2:$A$31) -> Finance | G26: =RIGHT(_xlfn.XLOOKUP(A26,'H&V'!$E$5:$AH$5,'H&V'!$E$3:$AH$3),1) -> 9
A27: Shodiyor Akbarov | B27: 9955 | C27: =_xlfn.XLOOKUP(A27,'H&V'!$B$4:$B$33,'H&V'!$A$4:$A$33,"Topilmadi") -> 0.07 | D27: =B27*(C27/100) -> 6.9685 | E27: =B27+D27 -> 9961.9685 | F27: =_xlfn.XLOOKUP(A27,ID!$B$2:$B$31,ID!$A$2:$A$31) -> Finance | G27: =RIGHT(_xlfn.XLOOKUP(A27,'H&V'!$E$5:$AH$5,'H&V'!$E$3:$AH$3),1) -> 5
A28: Jashon Raximov | B28: 4091 | C28: =_xlfn.XLOOKUP(A28,'H&V'!$B$4:$B$33,'H&V'!$A$4:$A$33,"Topilmadi") -> 0.05 | D28: =B28*(C28/100) -> 2.0455 | E28: =B28+D28 -> 4093.0455 | F28: =_xlfn.XLOOKUP(A28,ID!$B$2:$B$31,ID!$A$2:$A$31) -> Finance | G28: =RIGHT(_xlfn.XLOOKUP(A28,'H&V'!$E$5:$AH$5,'H&V'!$E$3:$AH$3),1) -> 6
... A31: Ilhomjon Raxmonov | B31: 8699 | C31: =_xlfn.XLOOKUP(A31,'H&V'!$B$4:$B$33,'H&V'!$A$4:$A$33,"Topilmadi") -> 0.06 | D31: =B31*(C31/100) -> 5.2194 | E31: =B31+D31 -> 8704.2194 | F31: =_xlfn.XLOOKUP(A31,ID!$B$2:$B$31,ID!$A$2:$A$31) -> Finance | G31: =RIGHT(_xlfn.XLOOKUP(A31,'H&V'!$E$5:$AH$5,'H&V'!$E$3:$AH$3),1) -> 7

Sheet H&V
D1: Horizontal
A2: Vertical
A3: Bonus % | B3: Employee Name | D3: EmployeID | E3: ID7 | F3: ID20 | G3: ID25 | H3: ID26 | I3: ID21 | J3: ID4 | K3: ID10 | L3: ID8 | M3: ID9 | N3: ID1 | O3: ID11 | P3: ID16 | Q3: ID29 | R3: ID27 | S3: ID15 | T3: ID12 | U3: ID19 | V3: ID24 | W3: ID3 | X3: ID14 | Y3: ID22 | Z3: ID13 | AA3: ID5 | AB3: ID17 | AC3: ID31 | AD3: ID32 | AE3: ID33 | AF3: ID34 | AG3: ID35 | AH3: ID36
A4: 0.27 | B4: Murod Karimov | D4: Bonus % | E4: 0.27 | F4: 0.25 | G4: 0.25 | H4: 0.25 | I4: 0.25 | J4: 0.24 | K4: 0.24 | L4: 0.23 | M4: 0.23 | N4: 0.21 | O4: 0.2 | P4: 0.19 | Q4: 0.18 | R4: 0.18 | S4: 0.17 | T4: 0.14 | U4: 0.14 | V4: 0.1 | W4: 0.1 | X4: 0.09 | Y4: 0.09 | Z4: 0.08 | AA4: 0.06 | AB4: 0.06 | AC4: 0.06 | AD4: 0.09 | AE4: 0.02 | AF4: 0.01 | AG4: 0.07 | AH4: 0.05
A5: 0.25 | B5: Ilhom Rahimov | D5: Employee Name | E5: Murod Karimov | F5: Ilhom Rahimov | G5: Jasur Aliyev | H5: Odil Abdullayev | I5: Sarvar Raxmonov | J5: Jasur Nurmatov | K5: Sarvar Karimov | L5: Dilshod Raxmonov | M5: Dilmurod Akbarov | N5: Aziz Raxmatov | O5: Javlon Soliyev | P5: Sardor Karimov | Q5: Komron Raxmonov | R5: Javlon Akbarov | S5: Shodlik Nurmatov | T5: Abduraxmon Toirov | U5: Jashon Alimov | V5: Jashon Abdullaev | W5: Shoxrux Yuldashev | X5: Akmal Toshpulatov | Y5: Bekzod Rustamov | Z5: Abdukarim Soliyev | AA5: Muhammad Akbarov | AB5: Ilhomjon Raxmonov | AC5: Abbos Karimov | AD5: Dilshod Rustamov | AE5: Bekzod Abdullaev | AF5: Ulugbek Soliyev | AG5: Shodiyor Akbarov | AH5: Jashon Raximov
A6: 0.25 | B6: Jasur Aliyev
A7: 0.25 | B7: Odil Abdullayev
A8: 0.25 | B8: Sarvar Raxmonov
A9: 0.24 | B9: Jasur Nurmatov
A10: 0.24 | B10: Sarvar Karimov
A11: 0.23 | B11: Dilshod Raxmonov
A12: 0.23 | B12: Dilmurod Akbarov
A13: 0.21 | B13: Aziz Raxmatov
A14: 0.2 | B14: Javlon Soliyev
A15: 0.19 | B15: Sardor Karimov
A16: 0.18 | B16: Komron Raxmonov
A17: 0.18 | B17: Javlon Akbarov
... A33: 0.05 | B33: Jashon Raximov
